dbchimaera/__init__.py
dbchimaera/core.py
dbchimaera-0.1.0.dist-info/METADATA
dbchimaera-0.1.0.dist-info/WHEEL
dbchimaera-0.1.0.dist-info/top_level.txt
dbchimaera-0.1.0.dist-info/RECORD
