Metadata-Version: 2.2
Name: dbchimaera
Version: 0.1.0
Summary: A shapeshifting database adapter that seamlessly handles syntax differences between database systems
Author-email: Your Name <your.email@example.com>
License: MIT
Project-URL: Homepage, https://github.com/dbchimaera/dbchimaera
Project-URL: Bug Tracker, https://github.com/dbchimaera/dbchimaera/issues
Classifier: Programming Language :: Python :: 3
Classifier: License :: OSI Approved :: MIT License
Classifier: Operating System :: OS Independent
Requires-Python: >=3.6
Requires-Dist: mysql-connector-python
